README.rst
setup.cfg
setup.py
vmd/__init__.py
vmd/default_formatters.py
vmd/elements.py
vmd/formatter.py
vmd/parser.py
vmd/renderer.py
vmd/styles.py
vmd/utils.py
vmd/writer.py
vmd.egg-info/PKG-INFO
vmd.egg-info/SOURCES.txt
vmd.egg-info/dependency_links.txt
vmd.egg-info/entry_points.txt
vmd.egg-info/requires.txt
vmd.egg-info/top_level.txt
vmd/config/__init__.py
vmd/config/config_reader.py
vmd/config/formatting_config.py
vmd/config/style_parser.py
vmd/config/styles_config.py
vmd/themes/default